{
  "collectionName": "components_dynamic_zone_welcome_banners",
  "info": {
    "displayName": "Welcome-Banner"
  },
  "options": {},
  "attributes": {
    "patient_image": {
      "type": "media",
      "multiple": false,
      "allowedTypes": [
        "images",
        "files",
        "videos",
        "audios"
      ]
    },
    "title": {
      "type": "string",
      "maxLength": 100
    },
    "description": {
      "type": "text",
      "maxLength": 400
    },
    "placeholder": {
      "type": "string",
      "maxLength": 30
    },
    "button_text": {
      "type": "string",
      "maxLength": 15
    },
    "whatsapp_number": {
      "type": "string",
      "maxLength": 10
    }
  },
  "config": {}
}
